benchproc/__init__.py
benchproc/engine.py
benchproc/task.py
benchmark_multiprocess-0.1.2.dist-info/LICENSE
benchmark_multiprocess-0.1.2.dist-info/METADATA
benchmark_multiprocess-0.1.2.dist-info/WHEEL
benchmark_multiprocess-0.1.2.dist-info/top_level.txt
benchmark_multiprocess-0.1.2.dist-info/RECORD
