Metadata-Version: 2.1
Name: benchmark-multiprocess
Version: 0.1.2
Summary: Simple Workflow Engine for Reproducible Benchmark Templates
Home-page: https://github.com/scailfin/benchmark-multiproc-backend
Author: Heiko Mueller
Author-email: heiko.muller@gmail.com
License: MIT
Keywords: reproducibility benchmarks data analysis
Platform: UNKNOWN
Classifier: License :: OSI Approved :: MIT License
Classifier: Operating System :: OS Independent
Classifier: Programming Language :: Python :: 3
Classifier: Programming Language :: Python :: 3.7
Classifier: Programming Language :: Python
Requires-Dist: benchmark-templates (>=0.1.2)
Provides-Extra: docs
Requires-Dist: Sphinx ; extra == 'docs'
Requires-Dist: sphinx-rtd-theme ; extra == 'docs'
Provides-Extra: tests
Requires-Dist: coverage (>=4.0) ; extra == 'tests'
Requires-Dist: pytest ; extra == 'tests'
Requires-Dist: pytest-cov ; extra == 'tests'
Requires-Dist: tox ; extra == 'tests'
